fds/__init__.py
fds/sdk/__init__.py
fds/sdk/FactSetGeoRev/__init__.py
fds/sdk/FactSetGeoRev/api_client.py
fds/sdk/FactSetGeoRev/configuration.py
fds/sdk/FactSetGeoRev/exceptions.py
fds/sdk/FactSetGeoRev/model_utils.py
fds/sdk/FactSetGeoRev/rest.py
fds/sdk/FactSetGeoRev/api/__init__.py
fds/sdk/FactSetGeoRev/api/countries_api.py
fds/sdk/FactSetGeoRev/api/regions_api.py
fds/sdk/FactSetGeoRev/apis/__init__.py
fds/sdk/FactSetGeoRev/model/__init__.py
fds/sdk/FactSetGeoRev/model/country.py
fds/sdk/FactSetGeoRev/model/country_ids.py
fds/sdk/FactSetGeoRev/model/country_request.py
fds/sdk/FactSetGeoRev/model/country_response.py
fds/sdk/FactSetGeoRev/model/error_response.py
fds/sdk/FactSetGeoRev/model/error_response_sub_errors.py
fds/sdk/FactSetGeoRev/model/frequency.py
fds/sdk/FactSetGeoRev/model/ids.py
fds/sdk/FactSetGeoRev/model/region.py
fds/sdk/FactSetGeoRev/model/region_ids.py
fds/sdk/FactSetGeoRev/model/region_request.py
fds/sdk/FactSetGeoRev/model/region_response.py
fds/sdk/FactSetGeoRev/models/__init__.py
fds.sdk.FactSetGeoRev-1.0.14.dist-info/LICENSE
fds.sdk.FactSetGeoRev-1.0.14.dist-info/METADATA
fds.sdk.FactSetGeoRev-1.0.14.dist-info/WHEEL
fds.sdk.FactSetGeoRev-1.0.14.dist-info/top_level.txt
fds.sdk.FactSetGeoRev-1.0.14.dist-info/RECORD
